backgammon/__init__.py
backgammon/example.py
backgammon/frontend/build/asset-manifest.json
backgammon/frontend/build/bootstrap.min.css
backgammon/frontend/build/index.html
backgammon/frontend/build/static/css/main.5ea8fc2e.css
backgammon/frontend/build/static/css/main.5ea8fc2e.css.map
backgammon/frontend/build/static/js/main.17f702b0.js
backgammon/frontend/build/static/js/main.17f702b0.js.LICENSE.txt
backgammon/frontend/build/static/js/main.17f702b0.js.map
backgammon/frontend/node_modules/flatted/python/flatted.py
backgammon/frontend/node_modules/flatted/python/test.py
e2e/e2e_utils.py
e2e/test_template.py
streamlit_backgammon-0.0.4.dist-info/LICENSE
streamlit_backgammon-0.0.4.dist-info/METADATA
streamlit_backgammon-0.0.4.dist-info/WHEEL
streamlit_backgammon-0.0.4.dist-info/top_level.txt
streamlit_backgammon-0.0.4.dist-info/RECORD
